{
  "unversionedId": "amtb/開示與問答/各地活動紀念影片/2009年山東青島企業家交流會第二屆花絮",
  "id": "amtb/開示與問答/各地活動紀念影片/2009年山東青島企業家交流會第二屆花絮",
  "isDocsHomePage": false,
  "title": "2009年山東青島企業家交流會(第二屆)花絮",
  "description": "",
  "source": "@site/docs/amtb/開示與問答/各地活動紀念影片/2009年山東青島企業家交流會第二屆花絮.mdx",
  "sourceDirName": "amtb/開示與問答/各地活動紀念影片",
  "slug": "/amtb/開示與問答/各地活動紀念影片/2009年山東青島企業家交流會第二屆花絮",
  "permalink": "/docs/amtb/開示與問答/各地活動紀念影片/2009年山東青島企業家交流會第二屆花絮",
  "editUrl": "https://github.com/l2yao/buddhacollege.org/edit/master/website/docs/amtb/開示與問答/各地活動紀念影片/2009年山東青島企業家交流會第二屆花絮.mdx",
  "version": "current",
  "sidebarPosition": 2273,
  "frontMatter": {
    "sidebar_position": 2273
  },
  "sidebar": "tutorialSidebar",
  "previous": {
    "title": "馬來西亞廬江文化教育中心啟用典禮",
    "permalink": "/docs/amtb/開示與問答/各地活動紀念影片/馬來西亞廬江文化教育中心啟用典禮"
  },
  "next": {
    "title": "香港書展",
    "permalink": "/docs/amtb/開示與問答/各地活動紀念影片/香港書展"
  }
}