{
  "unversionedId": "amtb/開示與問答/節錄/妄想執著是一切病苦的根源",
  "id": "amtb/開示與問答/節錄/妄想執著是一切病苦的根源",
  "isDocsHomePage": false,
  "title": "妄想執著是一切病苦的根源",
  "description": "",
  "source": "@site/docs/amtb/開示與問答/節錄/妄想執著是一切病苦的根源.mdx",
  "sourceDirName": "amtb/開示與問答/節錄",
  "slug": "/amtb/開示與問答/節錄/妄想執著是一切病苦的根源",
  "permalink": "/docs/amtb/開示與問答/節錄/妄想執著是一切病苦的根源",
  "editUrl": "https://github.com/l2yao/buddhacollege.org/edit/master/website/docs/amtb/開示與問答/節錄/妄想執著是一切病苦的根源.mdx",
  "version": "current",
  "sidebarPosition": 1156,
  "frontMatter": {
    "sidebar_position": 1156
  },
  "sidebar": "tutorialSidebar",
  "previous": {
    "title": "菩提心是念佛往生的本源",
    "permalink": "/docs/amtb/開示與問答/節錄/菩提心是念佛往生的本源"
  },
  "next": {
    "title": "知恩報恩",
    "permalink": "/docs/amtb/開示與問答/節錄/知恩報恩"
  }
}