{
  "unversionedId": "amtb/社會教育/多元文化/落實愛的教育促進世界和平二〇一八年威爾士穆斯林委員會跨宗教研討會",
  "id": "amtb/社會教育/多元文化/落實愛的教育促進世界和平二〇一八年威爾士穆斯林委員會跨宗教研討會",
  "isDocsHomePage": false,
  "title": "落實愛的教育促進世界和平——二〇一八年威爾士穆斯林委員會跨宗教研討會",
  "description": "",
  "source": "@site/docs/amtb/社會教育/多元文化/落實愛的教育促進世界和平二〇一八年威爾士穆斯林委員會跨宗教研討會.mdx",
  "sourceDirName": "amtb/社會教育/多元文化",
  "slug": "/amtb/社會教育/多元文化/落實愛的教育促進世界和平二〇一八年威爾士穆斯林委員會跨宗教研討會",
  "permalink": "/docs/amtb/社會教育/多元文化/落實愛的教育促進世界和平二〇一八年威爾士穆斯林委員會跨宗教研討會",
  "editUrl": "https://github.com/l2yao/buddhacollege.org/edit/master/website/docs/amtb/社會教育/多元文化/落實愛的教育促進世界和平二〇一八年威爾士穆斯林委員會跨宗教研討會.mdx",
  "version": "current",
  "sidebarPosition": 4989,
  "frontMatter": {
    "sidebar_position": 4989
  },
  "sidebar": "tutorialSidebar",
  "previous": {
    "title": "如何提高跨文化、跨宗教對話的效率——以「四攝法」促進社會和諧與寬容的經驗",
    "permalink": "/docs/amtb/社會教育/多元文化/如何提高跨文化跨宗教對話的效率以四攝法促進社會和諧與寬容的經驗"
  },
  "next": {
    "title": "為多元文化、多元宗教和諧共處「接棒」——二〇一八年聯合國教科文組織國際和平大會閉幕演講",
    "permalink": "/docs/amtb/社會教育/多元文化/為多元文化多元宗教和諧共處接棒二〇一八年聯合國教科文組織國際和平大會閉幕演講"
  }
}